{
  "data": [
    {
      "id": "2ee4497e-c326-4068-94ed-3dcdaaaa53bc",
      "name": "My_Mutator",
      "version": 2,
      "description": "This is a simple mutator",
      "columns": [
        {
          "name": "baz_column",
          "table": "users",
          "normalizer_id": "405d7cf0-e881-40a3-8e53-f76b502d2d76"
        }
      ],
      "access_policy": {
        "id": "0c0b7371-5175-405b-a17c-fec5969914b8",
        "name": "foo policy"
      },
      "selector_config": {
        "where_clause": "{id} = ?"
      }
    },
    {
      "id": "1aa4497e-c326-4068-94ed-3dcdaaaa53bc",
      "name": "My other mutator",
      "version": 1,
      "description": "This is a fairly simple mutator",
      "columns": [
        {
          "name": "bar_column",
          "table": "users",
          "normalizer_id": "405d7cf0-e881-40a3-8e53-f76b502d2d76"
        },
        {
          "name": "foo_column",
          "table": "users",
          "normalizer_id": "415d7cf0-e881-40a3-8e53-f76b502d2d76"
        }
      ],
      "access_policy": {
        "id": "6a0b7371-5175-405b-a17c-fec5969914b8",
        "name": "bar policy"
      },
      "selector_config": {
        "where_clause": "{id} = ?"
      }
    }
  ],
  "has_next": false,
  "next": "",
  "has_prev": false
}
